idotmatrix/__init__.py
idotmatrix/connectionManager.py
idotmatrix/const.py
idotmatrix/idotmatrix.py
idotmatrix/logger.py
idotmatrix/version.py
idotmatrix/modules/__init__.py
idotmatrix/modules/chronograph.py
idotmatrix/modules/clock.py
idotmatrix/modules/common.py
idotmatrix/modules/const.py
idotmatrix/modules/countdown.py
idotmatrix/modules/eco.py
idotmatrix/modules/effect.py
idotmatrix/modules/fullscreenColor.py
idotmatrix/modules/gif.py
idotmatrix/modules/graffiti.py
idotmatrix/modules/image.py
idotmatrix/modules/musicSync.py
idotmatrix/modules/scoreboard.py
idotmatrix/modules/system.py
idotmatrix/modules/text.py
idotmatrix-0.0.9.dist-info/LICENSE
idotmatrix-0.0.9.dist-info/METADATA
idotmatrix-0.0.9.dist-info/WHEEL
idotmatrix-0.0.9.dist-info/top_level.txt
idotmatrix-0.0.9.dist-info/RECORD
